podaac/__init__.py
podaac/forge_py/__init__.py
podaac/forge_py/args.py
podaac/forge_py/cli.py
podaac/forge_py/file_util.py
podaac/forge_py/forge.py
podaac/forge_py/strategies/alpha_shape_footprint.py
podaac/forge_py/strategies/open_cv_footprint.py
podaac/forge_py/strategies/shapely_linestring_footprint.py
podaac/lambda_handler/__init__.py
podaac/lambda_handler/cumulus_cli_handler/__init__.py
podaac/lambda_handler/cumulus_cli_handler/handlers.py
podaac/lambda_handler/lambda_handler.py
podaac/lambda_handler/lambda_handler_branch.py
podaac_forge_py-0.6.0.dist-info/LICENSE
podaac_forge_py-0.6.0.dist-info/METADATA
podaac_forge_py-0.6.0.dist-info/WHEEL
podaac_forge_py-0.6.0.dist-info/entry_points.txt
podaac_forge_py-0.6.0.dist-info/RECORD
