Metadata-Version: 2.3
Name: podaac-forge-py
Version: 0.6.0
Summary: forge-py is a footprint generator (FOotpRint GEnerator) from science data netcdf files
Author: James Wood
Author-email: James.F.Wood@jpl.nasa.gov
Requires-Python: >=3.11,<4.0
Classifier: Programming Language :: Python :: 3
Classifier: Programming Language :: Python :: 3.11
Classifier: Programming Language :: Python :: 3.12
Classifier: Programming Language :: Python :: 3.13
Requires-Dist: alphashape (>=1.3.1,<2.0.0)
Requires-Dist: cumulus-process (>=1.5.0,<2.0.0)
Requires-Dist: netcdf4 (>=1.6.5,<2.0.0)
Requires-Dist: np (>=1.0.2,<2.0.0)
Requires-Dist: numpy (<2.3.0)
Requires-Dist: opencv-python-headless (>=4.10.0.84,<5.0.0.0)
Requires-Dist: pillow (>=11.0.0,<12.0.0)
Requires-Dist: pyyaml (>=6.0,<7.0)
Requires-Dist: requests (>=2.31.0,<3.0.0)
Requires-Dist: shapely (>=2.0.3,<3.0.0)
Requires-Dist: xarray (>=2024.3.0,<2025.0.0)
